malmstin-0.0.1.dist-info/METADATA
malmstin-0.0.1.dist-info/WHEEL
malmstin-0.0.1.dist-info/licenses/LICENSE
malmstin/__init__.py
malmstin/foo.py
malmstin-0.0.1.dist-info/RECORD
