Metadata-Version: 2.1
Name: malmstin
Version: 0.0.1
Summary: Unveiling the Druggable Landscape: A Multimodal Approach (MALMSTIN)
Keywords: python
Author-Email: Carlos Loucera <carlos.loucera@juntadeandalucia.es>
License: MIT license
Project-URL: Homepage, https://loucerac.github.io/malmstin/
Project-URL: Repository, https://github.com/loucerac/malmstin
Project-URL: Documentation, https://loucerac.github.io/malmstin/
Requires-Python: <4.0,>=3.8
